README.rst
setup.py
mainutils/__init__.py
mainutils.egg-info/PKG-INFO
mainutils.egg-info/SOURCES.txt
mainutils.egg-info/dependency_links.txt
mainutils.egg-info/top_level.txt