Metadata-Version: 1.0
Name: mainutils
Version: 0.2.1
Summary: utilities for __main__
Home-page: https://github.com/ytyng/python-mainutils.git
Author: ytyng
Author-email: ytyng@live.jp
License: UNKNOWN
Keywords: Python main
Platform: UNKNOWN
